odoo/addons/hr_employee_emergency_contact/README.rst
odoo/addons/hr_employee_emergency_contact/__init__.py
odoo/addons/hr_employee_emergency_contact/__manifest__.py
odoo/addons/hr_employee_emergency_contact/i18n/ar.po
odoo/addons/hr_employee_emergency_contact/i18n/cs_CZ.po
odoo/addons/hr_employee_emergency_contact/i18n/de.po
odoo/addons/hr_employee_emergency_contact/i18n/es.po
odoo/addons/hr_employee_emergency_contact/i18n/fi.po
odoo/addons/hr_employee_emergency_contact/i18n/fr.po
odoo/addons/hr_employee_emergency_contact/i18n/hr.po
odoo/addons/hr_employee_emergency_contact/i18n/hr_HR.po
odoo/addons/hr_employee_emergency_contact/i18n/hr_emergency_contact.pot
odoo/addons/hr_employee_emergency_contact/i18n/hr_employee_emergency_contact.pot
odoo/addons/hr_employee_emergency_contact/i18n/it.po
odoo/addons/hr_employee_emergency_contact/i18n/lt.po
odoo/addons/hr_employee_emergency_contact/i18n/nl_NL.po
odoo/addons/hr_employee_emergency_contact/i18n/pt_BR.po
odoo/addons/hr_employee_emergency_contact/i18n/ro.po
odoo/addons/hr_employee_emergency_contact/i18n/sl.po
odoo/addons/hr_employee_emergency_contact/models/__init__.py
odoo/addons/hr_employee_emergency_contact/models/hr_employee.py
odoo/addons/hr_employee_emergency_contact/readme/CONTRIBUTORS.rst
odoo/addons/hr_employee_emergency_contact/readme/DESCRIPTION.rst
odoo/addons/hr_employee_emergency_contact/readme/INSTALL.rst
odoo/addons/hr_employee_emergency_contact/readme/USAGE.rst
odoo/addons/hr_employee_emergency_contact/static/description/icon.png
odoo/addons/hr_employee_emergency_contact/static/description/index.html
odoo/addons/hr_employee_emergency_contact/views/hr_employee_views.xml
odoo12_addon_hr_employee_emergency_contact-12.0.1.0.0.99.dev2.dist-info/METADATA
odoo12_addon_hr_employee_emergency_contact-12.0.1.0.0.99.dev2.dist-info/WHEEL
odoo12_addon_hr_employee_emergency_contact-12.0.1.0.0.99.dev2.dist-info/top_level.txt
odoo12_addon_hr_employee_emergency_contact-12.0.1.0.0.99.dev2.dist-info/RECORD
